rasteret/__init__.py
rasteret/cloud.py
rasteret/constants.py
rasteret/logging.py
rasteret/types.py
rasteret/core/__init__.py
rasteret/core/collection.py
rasteret/core/processor.py
rasteret/core/scene.py
rasteret/core/utils.py
rasteret/fetch/__init__.py
rasteret/fetch/cog.py
rasteret/stac/__init__.py
rasteret/stac/indexer.py
rasteret/stac/parser.py
rasteret/tests/test_cloud_provider.py
rasteret/tests/test_stac_indexer.py
rasteret-0.1.17.dist-info/LICENSE
rasteret-0.1.17.dist-info/METADATA
rasteret-0.1.17.dist-info/NOTICE
rasteret-0.1.17.dist-info/WHEEL
rasteret-0.1.17.dist-info/top_level.txt
rasteret-0.1.17.dist-info/RECORD
