Metadata-Version: 2.2
Name: rasteret
Version: 0.1.17
Summary: Fast and efficient access to Cloud-Optimized GeoTIFFs (COGs)
Home-page: https://github.com/terrafloww/rasteret
Author: Sidharth Subramaniam
Author-email: sid@terrafloww.com
Classifier: Development Status :: 4 - Beta
Classifier: Intended Audience :: Science/Research
Classifier: License :: OSI Approved :: Apache Software License
Classifier: Operating System :: OS Independent
Classifier: Programming Language :: Python :: 3.10
Classifier: Programming Language :: Python :: 3.11
Classifier: Topic :: Scientific/Engineering :: GIS
Classifier: Topic :: Scientific/Engineering :: Image Processing
Requires-Python: >=3.10,<3.12
License-File: LICENSE
License-File: NOTICE
Requires-Dist: numpy>=1.24.0
Requires-Dist: pyarrow>=14.0.1
Requires-Dist: pystac-client>=0.7.5
Requires-Dist: stac-geoparquet==0.6.0
Requires-Dist: aiohttp>=3.9.1
Requires-Dist: aiofiles>=23.2.1
Requires-Dist: cachetools>=5.3.2
Requires-Dist: geoarrow-pyarrow>=0.1.0
Requires-Dist: geoarrow-pandas>=0.1.0
Requires-Dist: boto3==1.18.32
Requires-Dist: xarray>=0.20.0
Requires-Dist: rioxarray>=0.7.0
Requires-Dist: imagecodecs>=2023.9.18
Requires-Dist: zstandard>=0.22.0
Requires-Dist: pyproj>=3.6.1
Requires-Dist: shapely>=2.0.2
Requires-Dist: affine>=2.4.0
Requires-Dist: rasterio>=1.4.0
Requires-Dist: tqdm>=4.66.1
Requires-Dist: rich>=13.7.0
Requires-Dist: pytest>=7.4.3
Requires-Dist: pytest-asyncio>=0.23.2
Requires-Dist: pytest-cov>=4.1.0
Requires-Dist: black>=23.12.1
Requires-Dist: ruff==0.8.6
Requires-Dist: isort>=5.13.2
Requires-Dist: flake8>=7.0.0
Requires-Dist: httpx[http2]
Provides-Extra: dev
Requires-Dist: pytest>=7.4.3; extra == "dev"
Requires-Dist: pytest-asyncio>=0.23.2; extra == "dev"
Requires-Dist: pytest-cov>=4.1.0; extra == "dev"
Requires-Dist: black>=23.12.1; extra == "dev"
Requires-Dist: ruff==0.8.6; extra == "dev"
Requires-Dist: isort>=5.13.2; extra == "dev"
Requires-Dist: flake8>=7.0.0; extra == "dev"
Requires-Dist: httpx[http2]; extra == "dev"
Dynamic: author
Dynamic: author-email
Dynamic: classifier
Dynamic: description
Dynamic: description-content-type
Dynamic: home-page
Dynamic: provides-extra
Dynamic: requires-dist
Dynamic: requires-python
Dynamic: summary
